matching_network/__init__.py
matching_network/__main__.py
matching_network/notmain.py
matching_network-0.1.6.dist-info/entry_points.txt
matching_network-0.1.6.dist-info/WHEEL
matching_network-0.1.6.dist-info/METADATA
matching_network-0.1.6.dist-info/RECORD
