Metadata-Version: 2.1
Name: matching-network
Version: 0.1.6
Summary: Design lumped-parameters matching networks (L-sections)
Home-page: https://pypi.org/project/matching-network/
License: MIT
Keywords: matching network,matching networks,l-section-matching,lumped-parameters-matching
Author: Francesco Urbani
Author-email: francescourbanidue@gmail.com
Requires-Python: >=3.6,<4.0
Classifier: License :: OSI Approved :: MIT License
Classifier: Programming Language :: Python :: 3
Classifier: Programming Language :: Python :: 3.6
Classifier: Programming Language :: Python :: 3.7
Classifier: Programming Language :: Python :: 3.8
Classifier: Programming Language :: Python :: 3.9
Requires-Dist: click (>=7.1.2,<8.0.0)
Requires-Dist: quantiphy (>=2.13.0,<3.0.0)
Project-URL: Repository, https://github.com/urbanij/matching-network
